sodastraw/__init__.py
sodastraw/sodastraw.py
sodastraw-0.0.0.dist-info/LICENSE
sodastraw-0.0.0.dist-info/METADATA
sodastraw-0.0.0.dist-info/WHEEL
sodastraw-0.0.0.dist-info/entry_points.txt
sodastraw-0.0.0.dist-info/top_level.txt
sodastraw-0.0.0.dist-info/RECORD
