Metadata-Version: 2.1
Name: sodastraw
Version: 0.0.0
Summary: Science image management on the web
Home-page: UNKNOWN
Author: Andy Kee
Author-email: UNKNOWN
License: UNKNOWN
Platform: any
Requires-Dist: requests
Requires-Dist: Pillow
Requires-Dist: numpy
Requires-Dist: matplotlib
